{
  "unknown": {
    "versionSfCore": null,
    "versionFramework": "4.2.5",
    "isWithinCompose": false,
    "composeOrgName": null,
    "composeServiceName": null,
    "command": [],
    "options": {
      "version": true
    },
    "error": null,
    "machineId": "32a2d3ef1d5963162a3c536eb563e518",
    "serviceProviderAwsCfStackId": null,
    "serviceProviderAwsCfStackCreated": null,
    "serviceProviderAwsCfStackUpdated": null,
    "serviceProviderAwsCfStackStatus": null,
    "serviceProviderAwsCfStackOutputs": null
  }
}